casino1v1/__init__.py
casino1v1/casino1v1.py
casino1v1-0.1.0.dist-info/LICENSE
casino1v1-0.1.0.dist-info/METADATA
casino1v1-0.1.0.dist-info/WHEEL
casino1v1-0.1.0.dist-info/entry_points.txt
casino1v1-0.1.0.dist-info/top_level.txt
casino1v1-0.1.0.dist-info/RECORD
