Metadata-Version: 2.2
Name: casino1v1
Version: 0.1.0
Summary: A humorous command-line Blackjack game.
Home-page: https://github.com/Snapout2/casino1v1.git
Author: Adarsh V H
Author-email: adarshvh2005@gmail.com
Classifier: Programming Language :: Python :: 3
Classifier: License :: OSI Approved :: MIT License
Classifier: Operating System :: OS Independent
Requires-Python: >=3.6
License-File: LICENSE
Dynamic: author
Dynamic: author-email
Dynamic: classifier
Dynamic: description
Dynamic: description-content-type
Dynamic: home-page
Dynamic: requires-python
Dynamic: summary
